ivoryos_client/__init__.py
ivoryos_client/client.py
ivoryos_client/exceptions.py
ivoryos_client-0.2.9.dist-info/licenses/LICENSE
ivoryos_client-0.2.9.dist-info/METADATA
ivoryos_client-0.2.9.dist-info/WHEEL
ivoryos_client-0.2.9.dist-info/top_level.txt
ivoryos_client-0.2.9.dist-info/RECORD
