Metadata-Version: 2.4
Name: ivoryos-client
Version: 0.2.9
Summary: Python client for IvoryOS workflow orchestrator
Author-email: Ivory Zhang <ivoryzhang@chem.ubc.ca>
Maintainer-email: Ivory Zhang <ivoryzhang@chem.ubc.ca>
License: MIT
Project-URL: Homepage, https://gitlab.com/heingroup/ivoryos-suite/ivoryos-client
Project-URL: Bug Tracker, https://gitlab.com/heingroup/ivoryos-suite/ivoryos-client/-/issues
Project-URL: Documentation, https://gitlab.com/heingroup/ivoryos-suite/ivoryos-client#readme
Project-URL: Source Code, https://gitlab.com/heingroup/ivoryos-suite/ivoryos-client
Keywords: ivoryos,workflow,orchestrator,automation,laboratory
Classifier: Development Status :: 3 - Alpha
Classifier: Intended Audience :: Developers
Classifier: Intended Audience :: Science/Research
Classifier: License :: OSI Approved :: MIT License
Classifier: Operating System :: OS Independent
Classifier: Programming Language :: Python :: 3
Classifier: Programming Language :: Python :: 3.8
Classifier: Programming Language :: Python :: 3.9
Classifier: Programming Language :: Python :: 3.10
Classifier: Programming Language :: Python :: 3.11
Classifier: Programming Language :: Python :: 3.12
Classifier: Topic :: Scientific/Engineering
Classifier: Topic :: Software Development :: Libraries :: Python Modules
Requires-Python: >=3.8
License-File: LICENSE
Requires-Dist: httpx>=0.24.0
Provides-Extra: dev
Requires-Dist: pytest>=7.0.0; extra == "dev"
Dynamic: license-file
